{
  "BurstVersion": "12fd8c57-ac57-41e8-88f3-e2a61ac3563b",
  "Assemblies": [
    {
      "FullName": "Unity.Burst, Version=0.0.0.0, Culture=neutral, PublicKeyToken=null",
      "LastWriteTime": "2021-03-17T08:29:04.7875186Z"
    },
    {
      "FullName": "netstandard, Version=2.0.0.0, Culture=neutral, PublicKeyToken=cc7b13ffcd2ddd51",
      "LastWriteTime": "2020-05-04T18:03:20Z"
    },
    {
      "FullName": "mscorlib, Version=4.0.0.0, Culture=neutral, PublicKeyToken=b77a5c561934e089",
      "LastWriteTime": "2020-05-04T18:03:20Z"
    }
  ],
  "Functions": [
    {
      "FullName": "System.Int32 Unity.Burst.Intrinsics.X86::DoGetCSRTrampoline()",
      "ModuleOptionsHash": 8794384452606821980,
      "ModuleHash": "70c4271591d26aed809e5ad65689a0ab",
      "LinkName": "CDCA4A5193BE5947",
      "AssemblyDependencyIndices": [
        0,
        1,
        2
      ]
    },
    {
      "FullName": "System.Void Unity.Burst.Intrinsics.X86::DoSetCSRTrampoline(System.Int32)",
      "ModuleOptionsHash": 8794384452606821980,
      "ModuleHash": "4f2d26ffb87c1f7e32f129a5d5f073f4",
      "LinkName": "801E9A000BB37B05",
      "AssemblyDependencyIndices": [
        0,
        1,
        2
      ]
    }
  ]
}